Metadata-Version: 1.1
Name: DataFrameManipulator
Version: 0.1
Summary: Used on top of pandas
Home-page: https://github.com/NyAinaLorenzo/DataFrameManipulator
Author: Ny Aina Lorenzo
Author-email: lolo.ramaromanana@gmail.com
License: MIT
Download-URL: https://github.com/NyAinaLorenzo/DataFrameManipulator/archive/v_0.1.tar.gz
Keywords: Data_frame,Manipulation
Platform: UNKNOWN
Classifier: Development Status :: 3 - Alpha
Classifier: Intended Audience :: Developers
Classifier: Topic :: Software Development :: Build Tools
Classifier: License :: OSI Approved :: MIT License
Classifier: Programming Language :: Python :: 3
Classifier: Programming Language :: Python :: 3.4
Classifier: Programming Language :: Python :: 3.5
Classifier: Programming Language :: Python :: 3.6
